hixbe_time/__init__.py
hixbe_time/cli/__init__.py
hixbe_time/core/__init__.py
hixbe_time/core/client.py
hixbe_time/core/parser.py
hixbe_time-1.0.0.dist-info/licenses/LICENSE
hixbe_time-1.0.0.dist-info/METADATA
hixbe_time-1.0.0.dist-info/WHEEL
hixbe_time-1.0.0.dist-info/entry_points.txt
hixbe_time-1.0.0.dist-info/top_level.txt
hixbe_time-1.0.0.dist-info/RECORD
