Metadata-Version: 2.4
Name: hixbe-time
Version: 1.0.0
Summary: High-precision NTP time synchronization package with CLI tools
Home-page: https://github.com/hixbehq/python-time
Author: Hixbe
Author-email: Hixbe <info@hixbe.com>
License: MIT
Project-URL: Homepage, https://github.com/hixbehq/python-time
Project-URL: Repository, https://github.com/hixbehq/python-time.git
Project-URL: Issues, https://github.com/hixbehq/python-time/issues
Keywords: ntp,network-time-protocol,time,synchronization,time-server,hixbe
Classifier: Development Status :: 5 - Production/Stable
Classifier: Intended Audience :: Developers
Classifier: License :: OSI Approved :: MIT License
Classifier: Operating System :: OS Independent
Classifier: Programming Language :: Python :: 3
Classifier: Programming Language :: Python :: 3.8
Classifier: Programming Language :: Python :: 3.9
Classifier: Programming Language :: Python :: 3.10
Classifier: Programming Language :: Python :: 3.11
Classifier: Programming Language :: Python :: 3.12
Classifier: Topic :: Software Development :: Libraries :: Python Modules
Classifier: Topic :: System :: Networking :: Time Synchronization
Requires-Python: >=3.8
License-File: LICENSE
Dynamic: author
Dynamic: home-page
Dynamic: license-file
Dynamic: requires-python
